{
  "type": "spectrum:titration_barrel",
  "group": "infused_beverages",
  "fermentation_time_days": 2,
  "ingredients": [
    {
      "item": "minecraft:sweet_berries",
      "count": 6
    },
    {
      "item": "spectrum:myceylon",
      "count": 4
    },
    {
      "item": "spectrum:prickly_bayleaf",
      "count": 4
    },
    {
      "item": "minecraft:sugar",
      "count": 4
    }
  ],
  "min_fermentation_time_hours": 48,
  "fluid": "minecraft:water",
  "tapping_item": "minecraft:glass_bottle",
  "fermentation_data": {
    "fermentation_speed_mod": 0.25,
    "effects": [
      {
        "id": "minecraft:speed",
        "base_duration": 9600,
        "potency": [
          {
            "potency": 0
          },
          {
            "min_alc": 20,
            "potency": 1
          },
          {
            "min_alc": 30,
            "potency": 2
          }
        ]
      },
      {
        "id": "spectrum:immunity",
        "base_duration": 2400,
        "potency": [
          {
            "min_alc": 22
          }
        ]
      },
      {
        "id": "minecraft:resistance",
        "base_duration": 2400,
        "potency": [
          {
            "min_alc": 25
          }
        ]
      },
      {
        "id": "minecraft:slowness",
        "base_duration": 9600,
        "potency": [
          {
            "min_thickness": 2
          },
          {
            "min_thickness": 3,
            "potency": 1
          },
          {
            "min_thickness": 4,
            "potency": 2
          }
        ]
      },
      {
        "id": "minecraft:blindness",
        "base_duration": 600,
        "potency": [
          {
            "min_thickness": 3
          },
          {
            "min_alc": 9
          }
        ]
      }
    ]
  },
  "result": {
    "item": "spectrum:infused_beverage",
    "count": 4,
    "nbt": "{Variant: \"spiked_mullet_wine\", Color: 10365209 }"
  },
  "required_advancement": "spectrum:progression/unlock_spiked_mullet_wine"
}