{
  "name": "Reprise",
  "advancement": "spectrum:progression/unlock_reprise",
  "icon": "spectrum:reprise",
  "category": "spectrum:magical_items_category",
  "extra_recipe_mappings": {
    "spectrum:reprise": 0
  },
  "pages": [
    {
      "type": "patchouli:text",
      "text": "This beverage, brewed from Chorus Fruit, takes over - and amplifies - not only the special taste, but also the unique property of the plant.$(br2)When ingested, this drink randomly teleports you over great distances. The higher the alcohol content, the further."
    },
    {
      "type": "spectrum:titration_barrel_fermenting",
      "title": "Titration Recipe",
      "recipe": "spectrum:titration_barrel/reprise",
      "text": "$(italic)What does it taste like? Most likely still like raspberry? But there are none in it at all. Strange."
    }
  ]
}