{
  "name": "Trifles",
  "icon": "spectrum:jaramel_trifle",
  "advancement": "spectrum:progression/unlock_trifles",
  "category": "spectrum:magical_items_category",
  "extra_recipe_mappings": {
    "spectrum:jaramel_trifle": 0,
    "spectrum:salted_jaramel_trifle": 0,
    "spectrum:monster_trifle": 0,
    "spectrum:tachycardia_trifle": 0
  },
  "pages": [
    {
      "type": "spectrum:pedestal_crafting",
      "title": "Jaramel Trifle",
      "recipe": "spectrum:pedestal/tier3/food/jaramel_trifle",
      "text": "Sweet delicacies, guaranteed to not only give you a sugar rush - depending on the toppings very intense, mostly $(thing)offensive$() ones. Made from $(l:resources/jade_vines#jaramel)Jaramel$(/l), $(thing)Milk$() & $(l:resources/amaranth)Amaranth$(/l). Even the rudimentary one tastes great! The only thing that would make it more delicious would be the tears of your enemies."
    },
    {
      "type": "spectrum:pedestal_crafting",
      "advancement": "spectrum:midgame/craft_salted_jaramel_trifle_or_tart",
      "recipe": "spectrum:pedestal/tier3/food/salted_jaramel_trifle",
      "text": "$(italic)Extra Salty"
    },
    {
      "type": "spectrum:pedestal_crafting",
      "recipe": "spectrum:pedestal/tier3/food/monster_trifle",
      "text": "Gives out effects at random. Fancy a gamble?"
    },
    {
      "type": "spectrum:pedestal_crafting",
      "recipe": "spectrum:pedestal/tier3/food/tachycardia_trifle",
      "text": "Chance to put you into $(thing)'Frenzy'$(): damage, attack speed, knockback resistance are buffed the more you kill. But if you do not score a kill in 20 seconds you get negative effects. Stacking $(thing)Frenzy$() increases it's potency instead."
    }
  ]
}
