{
  "type": "spectrum:fusion_shrine",
  "time": 600,
  "experience": 2.0,
  "fluid": "spectrum:liquid_crystal",
  "ingredients": [
    {
      "item": "spectrum:fanciful_stone_ring"
    },
    {
      "item": "minecraft:gold_ingot",
      "count": 8
    },
    {
      "item": "spectrum:moonstone_shard"
    },
    {
      "item": "spectrum:resonant_lily"
    }
  ],
  "result": {
    "item": "spectrum:neat_ring"
  },
  "required_advancement": "spectrum:progression/unlock_neat_ring",
  "world_conditions": [],
  "start_crafting_effect": "nothing",
  "during_crafting_effects": [],
  "finish_crafting_effect": "single_visual_explosion_on_shrine"
}