{
  "type": "spectrum:pedestal",
  "time": 1200,
  "tier": "advanced",
  "cyan": 4,
  "magenta": 0,
  "yellow": 0,
  "black": 1,
  "white": 0,
  "experience": 4.0,
  "pattern": [
    "OOO",
    "NGN",
    " N "
  ],
  "key": {
    "N": {
      "item": "spectrum:neolith"
    },
    "G": {
      "item": "spectrum:scarlet_gem"
    },
    "O": {
      "item": "spectrum:orange_pigment"
    }
  },
  "result": {
    "item": "spectrum:ashen_circlet",
    "count": 1
  },
  "required_advancements": ["spectrum:progression/unlock_ashen_circlet"]
}