{
  "name": "Production Surge",
  "advancement": "spectrum:lategame/collect_paletur",
  "secret": true,
  "icon": "spectrum:upgrade_yield",
  "category": "spectrum:magical_blocks_category",
  "extra_recipe_mappings": {
    "spectrum:upgrade_yield": 0,
    "spectrum:upgrade_yield2": 0
  },
  "pages": [
    {
      "type": "patchouli:text",
      "text": "This upgrade is an interesting one. Although the chance is very small, you can increase the amount of your crafting results.$(br2)$(italic)More bang for your buck!"
    },
    {
      "type": "spectrum:pedestal_crafting",
      "title": "Pedestal Recipe",
      "recipe": "spectrum:pedestal/tier4/upgrade_yield",
      "text": "Place on top your $(l:general/pedestal)Pigment Pedestals$(/l) Gemstone Blocks or the Chiseled Blocks of your $(l:general/fusion_shrine)Fusion Shrine$(/l). Additional ones have a decreased effect."
    },
    {
      "type": "spectrum:pedestal_crafting",
      "advancement": "spectrum:progression/unlock_upgrade_yield2",
      "title": "Tier 2",
      "recipe": "spectrum:pedestal/tier4/upgrade_yield2",
      "text": "This upgraded version is much more potent, allowing you to get even more output for your crafting."
    }
  ]
}
