{
  "name": "spectrum:pedestal_ruins/stone/side_rooms",
  "fallback": "minecraft:empty",
  "elements": [
    {
      "weight": 1,
      "element": {
        "element_type": "minecraft:single_pool_element",
        "location": "spectrum:pedestal_ruins/stone/side_0",
        "projection": "rigid",
        "processors": "minecraft:empty"
      }
    },
    {
      "weight": 1,
      "element": {
        "element_type": "minecraft:single_pool_element",
        "location": "spectrum:pedestal_ruins/stone/side_1",
        "projection": "rigid",
        "processors": "minecraft:empty"
      }
    },
    {
      "weight": 1,
      "element": {
        "element_type": "minecraft:single_pool_element",
        "location": "spectrum:pedestal_ruins/stone/side_2",
        "projection": "rigid",
        "processors": "minecraft:empty"
      }
    },
    {
      "weight": 2,
      "element": {
        "element_type": "minecraft:single_pool_element",
        "location": "spectrum:pedestal_ruins/stone/side_3",
        "projection": "rigid",
        "processors": "minecraft:empty"
      }
    }
  ]
}
