{
  "parent": "spectrum:midgame/collect_neolith",
  "display": {
    "icon": {
      "item": "spectrum:raw_azurite"
    },
    "title": {
      "translate": "advancements.spectrum.collect_azurite.title"
    },
    "description": {
      "translate": "advancements.spectrum.collect_azurite.description"
    },
    "hidden": true
  },
  "criteria": {
    "collected_azurite": {
      "trigger": "minecraft:inventory_changed",
      "conditions": {
        "items": [
          {
            "items": [
              "spectrum:raw_azurite",
              "spectrum:azurite_ore",
              "spectrum:deepslate_azurite_ore",
              "spectrum:blackslag_azurite_ore"
            ]
          }
        ]
      }
    },
    "gotten_previous": {
      "trigger":"revelationary:advancement_gotten",
      "conditions": { "advancement_identifier": "spectrum:midgame/collect_neolith" }
    }
  }
}