{
  "parent": "spectrum:midgame/drink_jade_wine",
  "display": {
    "icon": {
      "item": "spectrum:jade_wine"
    },
    "hidden": true,
    "title": {
      "translate": "advancements.spectrum.drink_sweetened_jade_wine.title"
    },
    "description": {
      "translate": "advancements.spectrum.drink_sweetened_jade_wine.description"
    }
  },
  "criteria": {
    "tapped_fermentation_barrel": {
      "trigger": "minecraft:consume_item",
      "conditions": {
        "item": {
          "items": [
            "spectrum:jade_wine"
          ],
          "nbt": "{Sweetened: 1b }"
        }
      }
    },
    "gotten_previous": {
      "trigger":"revelationary:advancement_gotten",
      "conditions": { "advancement_identifier": "spectrum:midgame/drink_jade_wine" }
    }
  }
}