{
  "criteria": {
    "built_enchanting_structure": {
      "trigger":"revelationary:advancement_gotten",
      "conditions": { "advancement_identifier": "spectrum:midgame/build_enchanting_structure" }
    },
    "collected_lightning_stone": {
      "trigger":"revelationary:advancement_gotten",
      "conditions": { "advancement_identifier": "spectrum:midgame/collect_lightning_stone" }
    },
    "collected_scarlet": {
      "trigger":"revelationary:advancement_gotten",
      "conditions": { "advancement_identifier": "spectrum:midgame/collect_scarlet" }
    }
  }
}