{
  "name": "Fundição",
  "icon": "minecraft:iron_pickaxe",
  "advancement": "spectrum:progression/enchantments/autosmelt",
  "category": "spectrum:enchanting_category",
  "pages": [
    {
      "type": "patchouli:text",
      "text": "$(italic)Você ainda lembra os primeiros dias nesse mundo, quando você tinha o trabalho de procurar carvão para queimar seus minérios. Mas esses dias estão contados, você jurou. O futuro é agora, velho.$(br2)Porém, tudo tem um preço: você perde a experiência que você normalmente ganharia assando o minério."
    },
    {
      "type": "patchouli:spotlight",
      "title": "Características",
      "item": "minecraft:iron_pickaxe{Enchantments: [{id: \"spectrum:autosmelt\", lvl: 1s}]}",
      "text": "Automáticamente assa blocos quebrados.$(br2)Nível Máximo: 1$(br)Aplicável a ferramentas de mineração.$(br)Mutualmente exclusivo a Toque Suave e Ressonância."
    },
    {
      "type": "spectrum:enchanter_crafting",
      "title": "Receita de Encantador",
      "recipe": "spectrum:enchanter/spectrum_books/book_autosmelt",
      "text": "Você pode infusionar um livro comum com Fundição rodeando seu Encantador com Pigmento e outros materiais necessários."
    }
  ]
}
